jason_gnss/__init__.py
jason_gnss/commands.py
jason_gnss/exif.py
jason_gnss/jason.py
jason_gnss/main.py
jason_gnss-1.13.1.dist-info/METADATA
jason_gnss-1.13.1.dist-info/WHEEL
jason_gnss-1.13.1.dist-info/entry_points.txt
jason_gnss-1.13.1.dist-info/top_level.txt
jason_gnss-1.13.1.dist-info/RECORD
