Metadata-Version: 2.1
Name: jason-gnss
Version: 1.13.1
Summary: Python bindings for Jason Cloud PPK Service: Rokubun GNSS processing engine in the cloud.
Home-page: https://github.com/rokubun/jason-sdk-python
Author: Rokubun
Author-email: info@rokubun.cat
License: http://opensource.org/licenses/MIT
Platform: UNKNOWN
Requires-Dist: docopt
Requires-Dist: requests
Requires-Dist: pytest
Requires-Dist: pytest-mocha
Requires-Dist: roktools
Requires-Dist: exifread
